WSI_handling/__init__.py
WSI_handling/annotation_handlers.py
WSI_handling/wsi.py
WSI_handling-0.16.2.dist-info/LICENSE.txt
WSI_handling-0.16.2.dist-info/METADATA
WSI_handling-0.16.2.dist-info/WHEEL
WSI_handling-0.16.2.dist-info/top_level.txt
WSI_handling-0.16.2.dist-info/RECORD
