Metadata-Version: 2.1
Name: WSI-handling
Version: 0.16.2
Summary: Convienent handling of annotated whole slide images
Home-page: https://github.com/pjl54/WSI_handling
Author: Patrick Leo
Author-email: pjl54@case.edu
License: MIT
Keywords: whole slide image,digital pathology,annotations
Platform: UNKNOWN
Classifier: Development Status :: 3 - Alpha
Classifier: Intended Audience :: Developers
Classifier: License :: OSI Approved :: MIT License
Classifier: Programming Language :: Python :: 3.8
Requires-Dist: Pillow
Requires-Dist: matplotlib
Requires-Dist: numpy
Requires-Dist: opencv-python
Requires-Dist: openslide-python
Requires-Dist: shapely
